mcp_openstack_ops/__init__.py
mcp_openstack_ops/__main__.py
mcp_openstack_ops/connection.py
mcp_openstack_ops/functions.py
mcp_openstack_ops/mcp_main.py
mcp_openstack_ops/services/__init__.py
mcp_openstack_ops/services/compute.py
mcp_openstack_ops/services/core.py
mcp_openstack_ops/services/identity.py
mcp_openstack_ops/services/image.py
mcp_openstack_ops/services/monitoring.py
mcp_openstack_ops/services/network.py
mcp_openstack_ops/services/orchestration.py
mcp_openstack_ops/services/storage.py
mcp_openstack_ops/services/load_balancer/__init__.py
mcp_openstack_ops/services/load_balancer/amphorae.py
mcp_openstack_ops/services/load_balancer/core.py
mcp_openstack_ops/services/load_balancer/health_monitors.py
mcp_openstack_ops/services/load_balancer/l7_policies.py
mcp_openstack_ops/services/load_balancer/listeners.py
mcp_openstack_ops/services/load_balancer/management.py
mcp_openstack_ops/services/load_balancer/pools.py
mcp_openstack_ops/tools/__init__.py
mcp_openstack_ops/tools/get_availability_zones.py
mcp_openstack_ops/tools/get_floating_ip_pools.py
mcp_openstack_ops/tools/get_floating_ips.py
mcp_openstack_ops/tools/get_heat_stacks.py
mcp_openstack_ops/tools/get_hypervisor_details.py
mcp_openstack_ops/tools/get_image_detail_list.py
mcp_openstack_ops/tools/get_instance.py
mcp_openstack_ops/tools/get_instance_by_name.py
mcp_openstack_ops/tools/get_instance_details.py
mcp_openstack_ops/tools/get_instances_by_status.py
mcp_openstack_ops/tools/get_keypair_list.py
mcp_openstack_ops/tools/get_load_balancer_amphorae.py
mcp_openstack_ops/tools/get_load_balancer_availability_zones.py
mcp_openstack_ops/tools/get_load_balancer_details.py
mcp_openstack_ops/tools/get_load_balancer_flavors.py
mcp_openstack_ops/tools/get_load_balancer_health_monitors.py
mcp_openstack_ops/tools/get_load_balancer_l7_policies.py
mcp_openstack_ops/tools/get_load_balancer_l7_rules.py
mcp_openstack_ops/tools/get_load_balancer_list.py
mcp_openstack_ops/tools/get_load_balancer_listeners.py
mcp_openstack_ops-3.3.4.dist-info/licenses/LICENSE
mcp_openstack_ops-3.3.4.dist-info/METADATA
mcp_openstack_ops-3.3.4.dist-info/WHEEL
mcp_openstack_ops-3.3.4.dist-info/entry_points.txt
mcp_openstack_ops-3.3.4.dist-info/top_level.txt
mcp_openstack_ops-3.3.4.dist-info/RECORD
