Metadata-Version: 2.4
Name: mcp-openstack-ops
Version: 3.3.4
Summary: OpenStack operations automation MCP server
Author-email: JungJungIn <call518@gmail.com>
Requires-Python: >=3.12
License-File: LICENSE
Requires-Dist: fastmcp>=2.12.3
Requires-Dist: openstacksdk<=4.8.0,>=4.1.0
Requires-Dist: python-dotenv>=1.1.1
Provides-Extra: dev
Requires-Dist: pytest>=7.0.0; extra == "dev"
Requires-Dist: pytest-asyncio>=0.21.0; extra == "dev"
Dynamic: license-file
